df_survey/__init__.py
df_survey/admin.py
df_survey/apps.py
df_survey/defaults.py
df_survey/models.py
df_survey/renderers.py
df_survey/resources.py
df_survey/settings.py
df_survey/utils.py
df_survey/drf/__init__.py
df_survey/drf/serializers.py
df_survey/drf/urls.py
df_survey/drf/viewsets.py
df_survey/migrations/0001_initial.py
df_survey/migrations/0002_auto_20231121_1208.py
df_survey/migrations/0003_alter_question_options_remove_survey_questions_and_more.py
df_survey/migrations/0004_alter_usersurvey_unique_together.py
df_survey/migrations/0005_alter_response_unique_together.py
df_survey/migrations/0006_question_text_alter_question_type.py
df_survey/migrations/0007_alter_question_type.py
df_survey/migrations/__init__.py
df_survey/static/df_survey/admin/css/surveys.css
df_survey/static/df_survey/admin/css/user_surveys.css
df_survey/static/df_survey/admin/js/survey-change-form.js
df_survey/templates/admin/df_survey/survey/assign_users.html
df_survey/templates/admin/df_survey/survey/change_form.html
df_survey/templates/admin/df_survey/survey/export_question_responses.html
df_survey/templates/admin/df_survey/survey/export_questions.html
df_survey/templates/admin/df_survey/survey/import_questions.html
df_survey/templates/df_notifications/usersurveynotification/body.html
df_survey/templates/df_notifications/usersurveynotification/body.txt
df_survey/templates/df_notifications/usersurveynotification/data.json
df_survey/templates/df_notifications/usersurveynotification/subject.txt
df_survey/templates/df_notifications/usersurveyreminder/body.html
df_survey/templates/df_notifications/usersurveyreminder/body.txt
df_survey/templates/df_notifications/usersurveyreminder/data.json
df_survey/templates/df_notifications/usersurveyreminder/subject.txt
django_df_survey-0.1.24.dist-info/LICENSE
django_df_survey-0.1.24.dist-info/METADATA
django_df_survey-0.1.24.dist-info/WHEEL
django_df_survey-0.1.24.dist-info/top_level.txt
django_df_survey-0.1.24.dist-info/RECORD
